orbital_core/__init__.py
orbital_core/app.py
orbital_core/routes/__init__.py
orbital_core/routes/docs.py
orbital_core/routes/templates/__init__.py
orbital_core/routes/templates/index.html
orbital_core/scripts/__init__.py
orbital_core/scripts/generate_swagger_json.py
orbital_core/tests/__init__.py
orbital_core/tests/conftest.py
orbital_core/tests/test_bootstrap_app.py
orbital_core/tests/docs/index.html
orbital_core/utils/__init__.py
orbital_core/utils/cors.py
orbital_core/utils/periodic_task.py
orbital_core-0.3.0.dist-info/LICENSE
orbital_core-0.3.0.dist-info/METADATA
orbital_core-0.3.0.dist-info/WHEEL
orbital_core-0.3.0.dist-info/entry_points.txt
orbital_core-0.3.0.dist-info/top_level.txt
orbital_core-0.3.0.dist-info/RECORD
