Metadata-Version: 2.1
Name: orbital-core
Version: 0.3.0
Summary: common code for orbital's aiohttp services
Home-page: UNKNOWN
Author: zillow-orbital
Author-email: UNKNOWN
License: UNKNOWN
Keywords: zillow
Platform: UNKNOWN
Classifier: Topic :: Utilities
Requires-Dist: aiohttp-transmute
Requires-Dist: aiohttp-cors
Requires-Dist: docopt
Requires-Dist: jinja2
